gorealtime/__init__.py
gorealtime/client.py
gorealtime/vendor/__init__.py
gorealtime/vendor/requests/__init__.py
gorealtime/vendor/requests/adapters.py
gorealtime/vendor/requests/api.py
gorealtime/vendor/requests/auth.py
gorealtime/vendor/requests/cacert.pem
gorealtime/vendor/requests/certs.py
gorealtime/vendor/requests/compat.py
gorealtime/vendor/requests/cookies.py
gorealtime/vendor/requests/exceptions.py
gorealtime/vendor/requests/hooks.py
gorealtime/vendor/requests/models.py
gorealtime/vendor/requests/sessions.py
gorealtime/vendor/requests/status_codes.py
gorealtime/vendor/requests/structures.py
gorealtime/vendor/requests/utils.py
gorealtime/vendor/requests/packages/__init__.py
gorealtime/vendor/requests/packages/chardet/__init__.py
gorealtime/vendor/requests/packages/chardet/big5freq.py
gorealtime/vendor/requests/packages/chardet/big5prober.py
gorealtime/vendor/requests/packages/chardet/chardetect.py
gorealtime/vendor/requests/packages/chardet/chardistribution.py
gorealtime/vendor/requests/packages/chardet/charsetgroupprober.py
gorealtime/vendor/requests/packages/chardet/charsetprober.py
gorealtime/vendor/requests/packages/chardet/codingstatemachine.py
gorealtime/vendor/requests/packages/chardet/compat.py
gorealtime/vendor/requests/packages/chardet/constants.py
gorealtime/vendor/requests/packages/chardet/cp949prober.py
gorealtime/vendor/requests/packages/chardet/escprober.py
gorealtime/vendor/requests/packages/chardet/escsm.py
gorealtime/vendor/requests/packages/chardet/eucjpprober.py
gorealtime/vendor/requests/packages/chardet/euckrfreq.py
gorealtime/vendor/requests/packages/chardet/euckrprober.py
gorealtime/vendor/requests/packages/chardet/euctwfreq.py
gorealtime/vendor/requests/packages/chardet/euctwprober.py
gorealtime/vendor/requests/packages/chardet/gb2312freq.py
gorealtime/vendor/requests/packages/chardet/gb2312prober.py
gorealtime/vendor/requests/packages/chardet/hebrewprober.py
gorealtime-0.1_dev.dist-info/DESCRIPTION.rst
gorealtime-0.1_dev.dist-info/METADATA
gorealtime-0.1_dev.dist-info/metadata.json
gorealtime-0.1_dev.dist-info/RECORD
gorealtime-0.1_dev.dist-info/top_level.txt
gorealtime-0.1_dev.dist-info/WHEEL
