Metadata-Version: 2.0
Name: gorealtime
Version: 0.1-dev
Summary: Python gorealtime client
Home-page: https://gorealtime.io
Author: Joe Alcorn
Author-email: joe@gorealtime.io
License: MIT
Platform: UNKNOWN
Classifier: Intended Audience :: Developers
Classifier: Natural Language :: English
Classifier: License :: OSI Approved :: MIT License
Classifier: Programming Language :: Python
Classifier: Programming Language :: Python :: 2.6
Classifier: Programming Language :: Python :: 2.7
Classifier: Programming Language :: Python :: 3
Classifier: Programming Language :: Python :: 3.3
